tinysvm/__init__.py
tinysvm-0.1.0.dist-info/licenses/LICENSE.txt
tinysvm-0.1.0.dist-info/METADATA
tinysvm-0.1.0.dist-info/WHEEL
tinysvm-0.1.0.dist-info/top_level.txt
tinysvm-0.1.0.dist-info/RECORD
