Metadata-Version: 2.4
Name: tinysvm
Version: 0.1.0
Summary: A lightweight, dependency-free (NumPy only) SVM implementation.
Author-email: "h-o-w-a-r-d(Iced_cocktails)" <howard-11-26@proton.me>
Project-URL: Homepage, https://github.com/h-o-w-a-r-d/TinySVM
Classifier: Programming Language :: Python :: 3
Classifier: License :: OSI Approved :: MIT License
Classifier: Operating System :: OS Independent
Classifier: Topic :: Scientific/Engineering :: Artificial Intelligence
Classifier: Intended Audience :: Education
Requires-Python: >=3.7
License-File: LICENSE.txt
Requires-Dist: numpy>=1.20.0
Dynamic: license-file
